anybot/__init__.py
anybot/__main__.py
anybot/action.py
anybot/bot.py
anybot/cli.py
anybot/utils.py
anybot-0.1.1.dist-info/DESCRIPTION.rst
anybot-0.1.1.dist-info/METADATA
anybot-0.1.1.dist-info/RECORD
anybot-0.1.1.dist-info/WHEEL
anybot-0.1.1.dist-info/entry_points.txt
anybot-0.1.1.dist-info/metadata.json
anybot-0.1.1.dist-info/top_level.txt
