Metadata-Version: 2.0
Name: anybot
Version: 0.1.1
Summary: Pluggable command line interface for automating online actions
Home-page: https://github.com/sentrip/anybot
Author: Djordje Pepic
Author-email: djordje.m.pepic@gmail.com
License: MIT license
Keywords: anybot
Platform: UNKNOWN
Classifier: Development Status :: 2 - Pre-Alpha
Classifier: Intended Audience :: Developers
Classifier: License :: OSI Approved :: MIT License
Classifier: Natural Language :: English
Classifier: Programming Language :: Python :: 2
Classifier: Programming Language :: Python :: 2.7
Classifier: Programming Language :: Python :: 3
Classifier: Programming Language :: Python :: 3.4
Classifier: Programming Language :: Python :: 3.5
Classifier: Programming Language :: Python :: 3.6
Classifier: Programming Language :: Python :: 3.7
Requires-Dist: Click (>=7.0)
